pyironflow/__init__.py
pyironflow/_version.py
pyironflow/pyironflow.py
pyironflow/reactflow.py
pyironflow/themes.py
pyironflow/treeview.py
pyironflow/wf_extensions.py
pyironflow-0.0.20.dist-info/licenses/LICENSE
pyironflow-0.0.20.dist-info/METADATA
pyironflow-0.0.20.dist-info/WHEEL
pyironflow-0.0.20.dist-info/top_level.txt
pyironflow-0.0.20.dist-info/RECORD
