Metadata-Version: 2.4
Name: pyironflow
Version: 0.0.20
Summary: react xyflow for pyiron
Author-email: "Max-Planck-Institut für Eisenforschung GmbH - Computational Materials Design (CM) Department" <pyiron@mpie.de>
License: BSD 3-Clause License
Project-URL: Homepage, https://github.com/pyiron/pyironFlow
Project-URL: Documentation, https://github.com/pyiron/pyironFlow
Project-URL: Repository, https://github.com/pyiron/pyironFlow
Keywords: pyiron
Classifier: Development Status :: 2 - Pre-Alpha
Classifier: Topic :: Scientific/Engineering :: Physics
Classifier: License :: OSI Approved :: BSD License
Classifier: Intended Audience :: Science/Research
Classifier: Operating System :: OS Independent
Classifier: Programming Language :: Python :: 3.11
Classifier: Programming Language :: Python :: 3.12
Requires-Python: <3.13,>=3.11
License-File: LICENSE
Requires-Dist: anywidget
Requires-Dist: traitlets
Requires-Dist: ipytree
Requires-Dist: ipython<9,>=8.11
Requires-Dist: ipywidgets
Requires-Dist: pyiron_workflow<1,>=0.12.1
Provides-Extra: dev
Requires-Dist: watchfiles; extra == "dev"
Requires-Dist: jupyterlab; extra == "dev"
Dynamic: license-file
